osmosis_wrap/__init__.py
osmosis_wrap/consts.py
osmosis_wrap/logger.py
osmosis_wrap/utils.py
osmosis_wrap/adapters/__init__.py
osmosis_wrap/adapters/anthropic.py
osmosis_wrap/adapters/langchain.py
osmosis_wrap/adapters/langchain_anthropic.py
osmosis_wrap/adapters/langchain_openai.py
osmosis_wrap/adapters/openai.py
osmosis_wrap-0.1.2.dist-info/licenses/LICENSE
osmosis_wrap-0.1.2.dist-info/METADATA
osmosis_wrap-0.1.2.dist-info/WHEEL
osmosis_wrap-0.1.2.dist-info/top_level.txt
osmosis_wrap-0.1.2.dist-info/RECORD
