Metadata-Version: 2.4
Name: osmosis-wrap
Version: 0.1.2
Summary: Monkey patches LLM client libraries to print all prompts and responses
Author-email: Gulp AI <jake@gulp.ai>
License: MIT License
Project-URL: Homepage, https://github.com/Gulp-AI/osmosis-wrap
Project-URL: Issues, https://github.com/Gulp-AI/osmosis-wrap/issues
Classifier: Programming Language :: Python :: 3
Classifier: License :: OSI Approved :: MIT License
Classifier: Operating System :: OS Independent
Requires-Python: >=3.6
License-File: LICENSE
Requires-Dist: python-dotenv>=0.19.0
Requires-Dist: requests>=2.25.0
Provides-Extra: anthropic
Requires-Dist: anthropic>=0.5.0; extra == "anthropic"
Provides-Extra: openai
Requires-Dist: openai>=0.27.0; extra == "openai"
Provides-Extra: langchain
Requires-Dist: langchain>=0.0.200; extra == "langchain"
Provides-Extra: langchain-openai
Requires-Dist: langchain>=0.0.200; extra == "langchain-openai"
Requires-Dist: langchain-openai>=0.0.200; extra == "langchain-openai"
Requires-Dist: openai>=0.27.0; extra == "langchain-openai"
Provides-Extra: langchain-anthropic
Requires-Dist: langchain>=0.0.200; extra == "langchain-anthropic"
Requires-Dist: langchain-anthropic>=0.0.200; extra == "langchain-anthropic"
Requires-Dist: anthropic>=0.5.0; extra == "langchain-anthropic"
Provides-Extra: all
Requires-Dist: anthropic>=0.5.0; extra == "all"
Requires-Dist: openai>=0.27.0; extra == "all"
Requires-Dist: langchain>=0.0.200; extra == "all"
Requires-Dist: langchain-openai>=0.0.200; extra == "all"
Requires-Dist: langchain-anthropic>=0.0.200; extra == "all"
Dynamic: license-file
